wlsonar/__init__.py
wlsonar/_client.py
wlsonar/_semver.py
wlsonar/_udp_helper.py
wlsonar/_xyz_helper.py
wlsonar/py.typed
wlsonar/range_image_protocol/__init__.py
wlsonar/range_image_protocol/_proto/WaterLinkedSonarIntegrationProtocol.proto
wlsonar/range_image_protocol/_proto/WaterLinkedSonarIntegrationProtocol_pb2.py
wlsonar/range_image_protocol/_proto/WaterLinkedSonarIntegrationProtocol_pb2.pyi
wlsonar/range_image_protocol/_protocol.py
wlsonar/range_image_protocol/py.typed
wlsonar-0.2.0.dist-info/WHEEL
wlsonar-0.2.0.dist-info/METADATA
wlsonar-0.2.0.dist-info/RECORD
