Metadata-Version: 2.3
Name: wlsonar
Version: 0.2.0
Summary: Python client and Range Image Protocol utilities for Water Linked Sonar 3D-15.
Author: Water Linked
Requires-Dist: protobuf>=6.33.2
Requires-Dist: python-snappy>=0.7.3
Requires-Dist: requests>=2.32.5
Requires-Python: >=3.10
